README.md
setup.py
tmcp/__init__.py
tmcp/convert.py
tmcp/handler.py
tmcp/message.py
tmcp/type_check.py
tmcp.egg-info/PKG-INFO
tmcp.egg-info/SOURCES.txt
tmcp.egg-info/dependency_links.txt
tmcp.egg-info/requires.txt
tmcp.egg-info/top_level.txt